digital_payments_sdk-1.2.0.dist-info/licenses/LICENSE
shellsmartpayapi/__init__.py
shellsmartpayapi/api_helper.py
shellsmartpayapi/configuration.py
shellsmartpayapi/shellsmartpayapi_client.py
shellsmartpayapi/controllers/__init__.py
shellsmartpayapi/controllers/base_controller.py
shellsmartpayapi/controllers/digital_payment_enablement_controller.py
shellsmartpayapi/controllers/fueling_controller.py
shellsmartpayapi/controllers/partner_notification_controller.py
shellsmartpayapi/controllers/shell_api_platform_security_authentication_controller.py
shellsmartpayapi/controllers/station_locator_controller.py
shellsmartpayapi/exceptions/__init__.py
shellsmartpayapi/exceptions/access_token_error_exception.py
shellsmartpayapi/exceptions/api_exception.py
shellsmartpayapi/exceptions/cancel_fueling_error_response_error_exception.py
shellsmartpayapi/exceptions/mpp_acces_token_error_response_exception.py
shellsmartpayapi/exceptions/payment_enablement_error_response_exception.py
shellsmartpayapi/exceptions/station_locator_bad_request_exception.py
shellsmartpayapi/exceptions/station_locator_forbidden_exception.py
shellsmartpayapi/exceptions/station_locator_internal_server_error_exception.py
shellsmartpayapi/exceptions/station_locator_not_found_exception.py
shellsmartpayapi/exceptions/station_locator_unauthorized_exception.py
shellsmartpayapi/http/__init__.py
shellsmartpayapi/http/http_call_back.py
shellsmartpayapi/http/http_method_enum.py
shellsmartpayapi/http/http_request.py
shellsmartpayapi/http/http_response.py
shellsmartpayapi/http/auth/__init__.py
shellsmartpayapi/http/auth/mpp_token.py
shellsmartpayapi/http/auth/o_auth_token_post.py
shellsmartpayapi/models/__init__.py
shellsmartpayapi/models/access_token_response.py
shellsmartpayapi/models/around_location_array.py
shellsmartpayapi/models/cancel_fueling_error_response.py
shellsmartpayapi/models/cancel_fueling_request.py
shellsmartpayapi/models/collecting_company.py
shellsmartpayapi/models/datum.py
shellsmartpayapi/models/detail.py
shellsmartpayapi/models/device_detail.py
digital_payments_sdk-1.2.0.dist-info/METADATA
digital_payments_sdk-1.2.0.dist-info/WHEEL
digital_payments_sdk-1.2.0.dist-info/top_level.txt
digital_payments_sdk-1.2.0.dist-info/RECORD
