Metadata-Version: 2.4
Name: digital-payments-sdk
Version: 1.2.0
Summary: The APIs detailed within this SDK will enable Shell's Fleet Solutions Customers to digitalize Shell Card/s and use them to pay to refuel their vehicles at Shell Stations.
Author-email: developer sdksio <developer+sdksio@apimatic.io>
Project-URL: Documentation, https://developer.shell.com/product-catalog/shell-smartpay-api/sdk#/http/setting-up-sdks
Keywords: Shell,APIMatic,SDKs,APIs,DigitalPayments
Requires-Python: >=3.7
License-File: LICENSE
Requires-Dist: apimatic-core>=0.2.17,~=0.2.0
Requires-Dist: apimatic-core-interfaces>=0.1.5,~=0.1.0
Requires-Dist: apimatic-requests-client-adapter>=0.1.6,~=0.1.0
Provides-Extra: testutils
Requires-Dist: pytest>=7.2.2; extra == "testutils"
Dynamic: license-file
